rnafbinv/IUPAC.py
rnafbinv/ListMotifs.py
rnafbinv/RNAfbinvCL.py
rnafbinv/mutator.py
rnafbinv/sfb_designer.py
rnafbinv/shapiro_generator.py
rnafbinv/shapiro_tree_aligner.py
rnafbinv/tree_aligner.py
rnafbinv/vienna.py
rnafbinv-2.0.4.dist-info/LICENSE
rnafbinv-2.0.4.dist-info/METADATA
rnafbinv-2.0.4.dist-info/WHEEL
rnafbinv-2.0.4.dist-info/top_level.txt
rnafbinv-2.0.4.dist-info/RECORD
