Metadata-Version: 2.1
Name: rnafbinv
Version: 2.0.4
Summary: Fragment based RNA designer
Home-page: https://github.com/matandro/RNAsfbinv
Author: Matan Drory Retwitzer
Author-email: matandro@post.bgu.ac.il
License: UNKNOWN
Platform: UNKNOWN
Classifier: Programming Language :: Python :: 3
Classifier: License :: OSI Approved :: MIT License
Classifier: Operating System :: OS Independent
Classifier: Topic :: Scientific/Engineering :: Bio-Informatics
Classifier: Intended Audience :: Science/Research
